[{"Id":"34130","Name":"Sal de ajo Hacendado","ShareUrl":"https://tienda.mercadona.es/product/34130/sal-ajo-hacendado-bote","Thumbnail":"https://prod-mercadona.imgix.net/images/bd81680a3655bf89428f333254f34979.jpg?fit=crop\u0026h=300\u0026w=300","UnitPrice":1.80,"UnitPriceString":"1,80 \u20AC/ud.","ReferencePrice":1.80,"ReferencePriceString":"1,80 \u20AC/kg","Packaging":"Bote 130 g","CategoryIds":[12,112,424]},{"Id":"34180","Name":"Or\u00E9gano Hacendado","ShareUrl":"https://tienda.mercadona.es/product/34180/oregano-hacendado-bote","Thumbnail":"https://prod-mercadona.imgix.net/images/fa759d1c372c34655489d608e5ab9244.jpg?fit=crop\u0026h=300\u0026w=300","UnitPrice":0.75,"UnitPriceString":"0,75 \u20AC/ud.","ReferencePrice":0.75,"ReferencePriceString":"0,75 \u20AC/100 g","Packaging":"Bote 18 g","CategoryIds":[12,115,425]},{"Id":"34131","Name":"Hierbas provenzales Hacendado","ShareUrl":"https://tienda.mercadona.es/product/34131/hierbas-provenzales-hacendado-bote","Thumbnail":"https://prod-mercadona.imgix.net/images/75ea233839587117b294f2d15027f57a.jpg?fit=crop\u0026h=300\u0026w=300","UnitPrice":1.20,"UnitPriceString":"1,20 \u20AC/ud.","ReferencePrice":1.20,"ReferencePriceString":"1,20 \u20AC/100 g","Packaging":"Bote 25 g","CategoryIds":[12,115,425]},{"Id":"34128","Name":"Albahaca Hacendado","ShareUrl":"https://tienda.mercadona.es/product/34128/albahaca-hacendado-bote","Thumbnail":"https://prod-mercadona.imgix.net/images/666740b544111126529a014431ba81f4.jpg?fit=crop\u0026h=300\u0026w=300","UnitPrice":1.25,"UnitPriceString":"1,25 \u20AC/ud.","ReferencePrice":1.25,"ReferencePriceString":"1,25 \u20AC/100 g","Packaging":"Bote 20 g","CategoryIds":[12,115,425]},{"Id":"34175","Name":"Romero Hacendado","ShareUrl":"https://tienda.mercadona.es/product/34175/romero-hacendado-bote","Thumbnail":"https://prod-mercadona.imgix.net/images/d5b59c36668ad99469b2c16a3d90fad7.jpg?fit=crop\u0026h=300\u0026w=300","UnitPrice":1.35,"UnitPriceString":"1,35 \u20AC/ud.","ReferencePrice":1.35,"ReferencePriceString":"1,35 \u20AC/100 g","Packaging":"Bote 40 g","CategoryIds":[12,115,425]},{"Id":"34136","Name":"Eneldo hojas Hacendado","ShareUrl":"https://tienda.mercadona.es/product/34136/eneldo-hojas-hacendado-bote","Thumbnail":"https://prod-mercadona.imgix.net/images/999403e34e3908d0daab771effeac05e.jpg?fit=crop\u0026h=300\u0026w=300","UnitPrice":1.85,"UnitPriceString":"1,85 \u20AC/ud.","ReferencePrice":1.85,"ReferencePriceString":"1,85 \u20AC/100 g","Packaging":"Bote 22 g","CategoryIds":[12,115,425]},{"Id":"34721","Name":"Cilantro Hacendado","ShareUrl":"https://tienda.mercadona.es/product/34721/cilantro-hacendado-bote","Thumbnail":"https://prod-mercadona.imgix.net/images/27379a6a13ab30cfb594a4b326f1f66c.jpg?fit=crop\u0026h=300\u0026w=300","UnitPrice":1.85,"UnitPriceString":"1,85 \u20AC/ud.","ReferencePrice":1.85,"ReferencePriceString":"1,85 \u20AC/100 g","Packaging":"Bote 12 g","CategoryIds":[12,115,425]},{"Id":"34182","Name":"Colorante alimentario Hacendado","ShareUrl":"https://tienda.mercadona.es/product/34182/colorante-alimentario-hacendado-bote","Thumbnail":"https://prod-mercadona.imgix.net/images/279afe277bed6a3c1af998dbda9b66e7.jpg?fit=crop\u0026h=300\u0026w=300","UnitPrice":0.90,"UnitPriceString":"0,90 \u20AC/ud.","ReferencePrice":0.90,"ReferencePriceString":"0,90 \u20AC/kg","Packaging":"Bote 85 g","CategoryIds":[12,115,840]},{"Id":"34184","Name":"Piment\u00F3n dulce Hacendado","ShareUrl":"https://tienda.mercadona.es/product/34184/pimenton-dulce-hacendado-bote","Thumbnail":"https://prod-mercadona.imgix.net/images/d01141fdec8c11a291e21f084d94f43c.jpg?fit=crop\u0026h=300\u0026w=300","UnitPrice":0.95,"UnitPriceString":"0,95 \u20AC/ud.","ReferencePrice":0.95,"ReferencePriceString":"0,95 \u20AC/kg","Packaging":"Bote 56 g","CategoryIds":[12,115,840]},{"Id":"34186","Name":"Piment\u00F3n dulce Hacendado","ShareUrl":"https://tienda.mercadona.es/product/34186/pimenton-dulce-hacendado-bote","Thumbnail":"https://prod-mercadona.imgix.net/images/f36ba84f3f573b9dd2c12d3ba617df4c.jpg?fit=crop\u0026h=300\u0026w=300","UnitPrice":1.40,"UnitPriceString":"1,40 \u20AC/ud.","ReferencePrice":1.40,"ReferencePriceString":"1,40 \u20AC/kg","Packaging":"Bote 75 g","CategoryIds":[12,115,840]},{"Id":"34102","Name":"Piment\u00F3n dulce de la Vera Hacendado","ShareUrl":"https://tienda.mercadona.es/product/34102/pimenton-dulce-vera-hacendado-bote","Thumbnail":"https://prod-mercadona.imgix.net/images/a6d68b421b2643e1a408ef4d960ac575.jpg?fit=crop\u0026h=300\u0026w=300","UnitPrice":1.55,"UnitPriceString":"1,55 \u20AC/ud.","ReferencePrice":1.55,"ReferencePriceString":"1,55 \u20AC/kg","Packaging":"Bote 75 g","CategoryIds":[12,115,840]},{"Id":"34116","Name":"Azafr\u00E1n molido Hacendado","ShareUrl":"https://tienda.mercadona.es/product/34116/azafran-molido-hacendado-paquete","Thumbnail":"https://prod-mercadona.imgix.net/images/d79e295f90865210d4a83792f316b66a.jpg?fit=crop\u0026h=300\u0026w=300","UnitPrice":1.75,"UnitPriceString":"1,75 \u20AC/ud.","ReferencePrice":1.75,"ReferencePriceString":"1,75 \u20AC/100 g","Packaging":"Paquete 4 sobres (0 g)","CategoryIds":[12,115,840]},{"Id":"34115","Name":"Azafr\u00E1n hebra Hacendado","ShareUrl":"https://tienda.mercadona.es/product/34115/azafran-hebra-hacendado-paquete","Thumbnail":"https://prod-mercadona.imgix.net/images/6b28a5275722bf42ecd58cac70a7497f.jpg?fit=crop\u0026h=300\u0026w=300","UnitPrice":1.70,"UnitPriceString":"1,70 \u20AC/ud.","ReferencePrice":1.70,"ReferencePriceString":"1,70 \u20AC/100 g","Packaging":"Paquete 3 usos (0 g)","CategoryIds":[12,115,840]},{"Id":"34183","Name":"Piment\u00F3n picante Hacendado","ShareUrl":"https://tienda.mercadona.es/product/34183/pimenton-picante-hacendado-bote","Thumbnail":"https://prod-mercadona.imgix.net/images/2f865dc2dc829da4a0e2962fb922cd9c.jpg?fit=crop\u0026h=300\u0026w=300","UnitPrice":1.35,"UnitPriceString":"1,35 \u20AC/ud.","ReferencePrice":1.35,"ReferencePriceString":"1,35 \u20AC/kg","Packaging":"Bote 60 g","CategoryIds":[12,115,840]},{"Id":"34171","Name":"Pimienta negra molida Hacendado","ShareUrl":"https://tienda.mercadona.es/product/34171/pimienta-negra-molida-hacendado-bote","Thumbnail":"https://prod-mercadona.imgix.net/images/905e76fd8f59b3931ae5e2c586c4a9f5.jpg?fit=crop\u0026h=300\u0026w=300","UnitPrice":1.05,"UnitPriceString":"1,05 \u20AC/ud.","ReferencePrice":1.05,"ReferencePriceString":"1,05 \u20AC/kg","Packaging":"Bote 70 g","CategoryIds":[12,115,841]},{"Id":"34172","Name":"Pimienta negra en grano Hacendado","ShareUrl":"https://tienda.mercadona.es/product/34172/pimienta-negra-grano-hacendado-bote","Thumbnail":"https://prod-mercadona.imgix.net/images/ade2f829444a465f07de05c97b526258.jpg?fit=crop\u0026h=300\u0026w=300","UnitPrice":1.45,"UnitPriceString":"1,45 \u20AC/ud.","ReferencePrice":1.45,"ReferencePriceString":"1,45 \u20AC/kg","Packaging":"Bote 70 g","CategoryIds":[12,115,841]},{"Id":"34170","Name":"Pimienta blanca molida Hacendado","ShareUrl":"https://tienda.mercadona.es/product/34170/pimienta-blanca-molida-hacendado-bote","Thumbnail":"https://prod-mercadona.imgix.net/images/a8cedadb6026482169a838838a6943d3.jpg?fit=crop\u0026h=300\u0026w=300","UnitPrice":2.15,"UnitPriceString":"2,15 \u20AC/ud.","ReferencePrice":2.15,"ReferencePriceString":"2,15 \u20AC/kg","Packaging":"Bote 70 g","CategoryIds":[12,115,841]},{"Id":"34208","Name":"Cebolla frita crujiente Hacendado","ShareUrl":"https://tienda.mercadona.es/product/34208/cebolla-frita-crujiente-hacendado-bote","Thumbnail":"https://prod-mercadona.imgix.net/images/fb2e63195fc20b44ae5f3598c40a7565.jpg?fit=crop\u0026h=300\u0026w=300","UnitPrice":1.15,"UnitPriceString":"1,15 \u20AC/ud.","ReferencePrice":1.15,"ReferencePriceString":"1,15 \u20AC/kg","Packaging":"Bote 150 g","CategoryIds":[12,115,431]},{"Id":"34177","Name":"Canela molida Hacendado","ShareUrl":"https://tienda.mercadona.es/product/34177/canela-molida-hacendado-bote","Thumbnail":"https://prod-mercadona.imgix.net/images/22948761cf10a9f149a06ec505fb8dcd.jpg?fit=crop\u0026h=300\u0026w=300","UnitPrice":0.95,"UnitPriceString":"0,95 \u20AC/ud.","ReferencePrice":0.95,"ReferencePriceString":"0,95 \u20AC/kg","Packaging":"Bote 52 g","CategoryIds":[12,115,431]},{"Id":"34176","Name":"Canela en rama Hacendado","ShareUrl":"https://tienda.mercadona.es/product/34176/canela-rama-hacendado-bote","Thumbnail":"https://prod-mercadona.imgix.net/images/70fde90857e0a442eccad1479826a52d.jpg?fit=crop\u0026h=300\u0026w=300","UnitPrice":1.35,"UnitPriceString":"1,35 \u20AC/ud.","ReferencePrice":1.35,"ReferencePriceString":"1,35 \u20AC/100 g","Packaging":"Bote 18 g","CategoryIds":[12,115,431]},{"Id":"34120","Name":"Comino molido Hacendado","ShareUrl":"https://tienda.mercadona.es/product/34120/comino-molido-hacendado-bote","Thumbnail":"https://prod-mercadona.imgix.net/images/003c9821946990d15215928c180ec0b7.jpg?fit=crop\u0026h=300\u0026w=300","UnitPrice":1.00,"UnitPriceString":"1,00 \u20AC/ud.","ReferencePrice":1.00,"ReferencePriceString":"1,00 \u20AC/kg","Packaging":"Bote 58 g","CategoryIds":[12,115,431]},{"Id":"34121","Name":"Comino en grano Hacendado","ShareUrl":"https://tienda.mercadona.es/product/34121/comino-grano-hacendado-bote","Thumbnail":"https://prod-mercadona.imgix.net/images/945a39457b8b947b612650a22e7a2c71.jpg?fit=crop\u0026h=300\u0026w=300","UnitPrice":1.95,"UnitPriceString":"1,95 \u20AC/ud.","ReferencePrice":1.95,"ReferencePriceString":"1,95 \u20AC/kg","Packaging":"Bote 56 g","CategoryIds":[12,115,431]},{"Id":"34125","Name":"Curry Hacendado","ShareUrl":"https://tienda.mercadona.es/product/34125/curry-hacendado-bote","Thumbnail":"https://prod-mercadona.imgix.net/images/41e788d61332bbabe67bcb18c9b74d9e.jpg?fit=crop\u0026h=300\u0026w=300","UnitPrice":1.15,"UnitPriceString":"1,15 \u20AC/ud.","ReferencePrice":1.15,"ReferencePriceString":"1,15 \u20AC/kg","Packaging":"Bote 57 g","CategoryIds":[12,115,431]},{"Id":"34173","Name":"Nuez moscada molida Hacendado","ShareUrl":"https://tienda.mercadona.es/product/34173/nuez-moscada-molida-hacendado-bote","Thumbnail":"https://prod-mercadona.imgix.net/images/26a3c69f637bdb1722940dbaa79f6cf9.jpg?fit=crop\u0026h=300\u0026w=300","UnitPrice":1.65,"UnitPriceString":"1,65 \u20AC/ud.","ReferencePrice":1.65,"ReferencePriceString":"1,65 \u20AC/kg","Packaging":"Bote 58 g","CategoryIds":[12,115,431]},{"Id":"34138","Name":"Cebolla en polvo Hacendado","ShareUrl":"https://tienda.mercadona.es/product/34138/cebolla-polvo-hacendado-bote","Thumbnail":"https://prod-mercadona.imgix.net/images/4e60df323518b37ef8fcc6be6103526e.jpg?fit=crop\u0026h=300\u0026w=300","UnitPrice":0.96,"UnitPriceString":"0,96 \u20AC/ud.","ReferencePrice":0.96,"ReferencePriceString":"0,96 \u20AC/kg","Packaging":"Bote 60 g","CategoryIds":[12,115,431]},{"Id":"34178","Name":"Cayena guindillas Hacendado","ShareUrl":"https://tienda.mercadona.es/product/34178/cayena-guindillas-hacendado-bote","Thumbnail":"https://prod-mercadona.imgix.net/images/ca1ef5080300ea3323d59f0911f471db.jpg?fit=crop\u0026h=300\u0026w=300","UnitPrice":1.30,"UnitPriceString":"1,30 \u20AC/ud.","ReferencePrice":1.30,"ReferencePriceString":"1,30 \u20AC/100 g","Packaging":"Bote 27 g","CategoryIds":[12,115,431]},{"Id":"34163","Name":"C\u00FArcuma Hacendado","ShareUrl":"https://tienda.mercadona.es/product/34163/curcuma-hacendado-bote","Thumbnail":"https://prod-mercadona.imgix.net/images/bbb23780061cfd84ea7c8b8890715380.jpg?fit=crop\u0026h=300\u0026w=300","UnitPrice":1.25,"UnitPriceString":"1,25 \u20AC/ud.","ReferencePrice":1.25,"ReferencePriceString":"1,25 \u20AC/kg","Packaging":"Bote 60 g","CategoryIds":[12,115,431]},{"Id":"34149","Name":"Jengibre molido Hacendado","ShareUrl":"https://tienda.mercadona.es/product/34149/jengibre-molido-hacendado-bote","Thumbnail":"https://prod-mercadona.imgix.net/images/660b9d830317ff63daa0a5a5cfe4cdb2.jpg?fit=crop\u0026h=300\u0026w=300","UnitPrice":1.60,"UnitPriceString":"1,60 \u20AC/ud.","ReferencePrice":1.60,"ReferencePriceString":"1,60 \u20AC/100 g","Packaging":"Bote 49 g","CategoryIds":[12,115,431]},{"Id":"34113","Name":"\u00D1oras Hacendado","ShareUrl":"https://tienda.mercadona.es/product/34113/noras-hacendado-paquete","Thumbnail":"https://prod-mercadona.imgix.net/images/4e524d80be3b75f95866a26e9f551356.jpg?fit=crop\u0026h=300\u0026w=300","UnitPrice":1.40,"UnitPriceString":"1,40 \u20AC/ud.","ReferencePrice":1.40,"ReferencePriceString":"1,40 \u20AC/100 g","Packaging":"Paquete 25 g","CategoryIds":[12,115,431]},{"Id":"34122","Name":"Clavo en grano Hacendado","ShareUrl":"https://tienda.mercadona.es/product/34122/clavo-grano-hacendado-bote","Thumbnail":"https://prod-mercadona.imgix.net/images/4454375471a75b1e36fe451869e79460.jpg?fit=crop\u0026h=300\u0026w=300","UnitPrice":1.75,"UnitPriceString":"1,75 \u20AC/ud.","ReferencePrice":1.75,"ReferencePriceString":"1,75 \u20AC/100 g","Packaging":"Bote 42 g","CategoryIds":[12,115,431]},{"Id":"34123","Name":"An\u00EDs en grano Hacendado","ShareUrl":"https://tienda.mercadona.es/product/34123/anis-grano-hacendado-bote","Thumbnail":"https://prod-mercadona.imgix.net/images/8a0d0e5176f9c1a26fcd7cb0e7c2af49.jpg?fit=crop\u0026h=300\u0026w=300","UnitPrice":1.90,"UnitPriceString":"1,90 \u20AC/ud.","ReferencePrice":1.90,"ReferencePriceString":"1,90 \u20AC/kg","Packaging":"Bote 50 g","CategoryIds":[12,115,431]},{"Id":"34777","Name":"Preparado para paella con azafr\u00E1n Hacendado","ShareUrl":"https://tienda.mercadona.es/product/34777/preparado-paella-con-azafran-hacendado-bote","Thumbnail":"https://prod-mercadona.imgix.net/images/f522c66e4e5f014821d734cf1aaaa9e1.jpg?fit=crop\u0026h=300\u0026w=300","UnitPrice":1.85,"UnitPriceString":"1,85 \u20AC/ud.","ReferencePrice":1.85,"ReferencePriceString":"1,85 \u20AC/kg","Packaging":"Bote 76 g","CategoryIds":[12,115,430]},{"Id":"34702","Name":"Sazonador para paella con azafr\u00E1n Hacendado","ShareUrl":"https://tienda.mercadona.es/product/34702/sazonador-paella-con-azafran-hacendado-caja","Thumbnail":"https://prod-mercadona.imgix.net/images/f2cdac44f287c5a2b6d89b51d091ad3e.jpg?fit=crop\u0026h=300\u0026w=300","UnitPrice":1.40,"UnitPriceString":"1,40 \u20AC/ud.","ReferencePrice":1.40,"ReferencePriceString":"1,40 \u20AC/100 g","Packaging":"Caja 5 sobres (20 g)","CategoryIds":[12,115,430]},{"Id":"34134","Name":"Sazonador pasta Hacendado","ShareUrl":"https://tienda.mercadona.es/product/34134/sazonador-pasta-hacendado-bote","Thumbnail":"https://prod-mercadona.imgix.net/images/6369ccef5e52514b25f82ea3a6562698.jpg?fit=crop\u0026h=300\u0026w=300","UnitPrice":2.50,"UnitPriceString":"2,50 \u20AC/ud.","ReferencePrice":2.50,"ReferencePriceString":"2,50 \u20AC/100 g","Packaging":"Bote 45 g","CategoryIds":[12,115,430]},{"Id":"34114","Name":"Mezcla de especias para gazpacho manchego Hacendado","ShareUrl":"https://tienda.mercadona.es/product/34114/mezcla-especias-gazpacho-manchego-hacendado-caja","Thumbnail":"https://prod-mercadona.imgix.net/images/1da0d4f205b99554f8c4e5d9b00a82a8.jpg?fit=crop\u0026h=300\u0026w=300","UnitPrice":2.50,"UnitPriceString":"2,50 \u20AC/ud.","ReferencePrice":2.50,"ReferencePriceString":"2,50 \u20AC/100 g","Packaging":"Caja 5 sobres (10 g)","CategoryIds":[12,115,430]},{"Id":"34157","Name":"Carne de pimiento choricero Hacendado","ShareUrl":"https://tienda.mercadona.es/product/34157/carne-pimiento-choricero-hacendado-tarro","Thumbnail":"https://prod-mercadona.imgix.net/images/9e50c105104706ffbc3a73c66453c47c.jpg?fit=crop\u0026h=300\u0026w=300","UnitPrice":1.55,"UnitPriceString":"1,55 \u20AC/ud.","ReferencePrice":1.55,"ReferencePriceString":"1,55 \u20AC/kg","Packaging":"Tarro 140 g","CategoryIds":[12,117,440]},{"Id":"34024","Name":"Nuez natural Hacendado pelada","ShareUrl":"https://tienda.mercadona.es/product/34024/nuez-natural-hacendado-pelada-paquete","Thumbnail":"https://prod-mercadona.imgix.net/images/de768af5358346867a912d57ec96b69c.jpg?fit=crop\u0026h=300\u0026w=300","UnitPrice":2.15,"UnitPriceString":"2,15 \u20AC/ud.","ReferencePrice":2.15,"ReferencePriceString":"2,15 \u20AC/kg","Packaging":"Paquete 200 g","CategoryIds":[15,133,479]},{"Id":"34865","Name":"Almendra natural Hacendado","ShareUrl":"https://tienda.mercadona.es/product/34865/almendra-natural-hacendado-paquete","Thumbnail":"https://prod-mercadona.imgix.net/images/ce65d25f356634d8815d2f4a208447f7.jpg?fit=crop\u0026h=300\u0026w=300","UnitPrice":2.20,"UnitPriceString":"2,20 \u20AC/ud.","ReferencePrice":2.20,"ReferencePriceString":"2,20 \u20AC/kg","Packaging":"Paquete 200 g","CategoryIds":[15,133,479]},{"Id":"34079","Name":"Pipas girasol tostadas Hacendado gigante con sal","ShareUrl":"https://tienda.mercadona.es/product/34079/pipas-girasol-tostadas-hacendado-gigante-con-sal-paquete","Thumbnail":"https://prod-mercadona.imgix.net/images/f78cd0cf76d9aeee2701418caac6a213.jpg?fit=crop\u0026h=300\u0026w=300","UnitPrice":1.20,"UnitPriceString":"1,20 \u20AC/ud.","ReferencePrice":1.20,"ReferencePriceString":"1,20 \u20AC/kg","Packaging":"Paquete 200 g","CategoryIds":[15,133,479]},{"Id":"34820","Name":"Cacahuete frito con sal Hacendado pelado","ShareUrl":"https://tienda.mercadona.es/product/34820/cacahuete-frito-con-sal-hacendado-pelado-paquete","Thumbnail":"https://prod-mercadona.imgix.net/images/9ab4072fb0bccc62654a11f957c20b96.jpg?fit=crop\u0026h=300\u0026w=300","UnitPrice":1.05,"UnitPriceString":"1,05 \u20AC/ud.","ReferencePrice":1.05,"ReferencePriceString":"1,05 \u20AC/kg","Packaging":"Paquete 250 g","CategoryIds":[15,133,479]},{"Id":"34078","Name":"Pipas girasol tostadas Hacendado gigante aguasal","ShareUrl":"https://tienda.mercadona.es/product/34078/pipas-girasol-tostadas-hacendado-gigante-aguasal-paquete","Thumbnail":"https://prod-mercadona.imgix.net/images/65128d654c1a2f4d7dfc8859e95d4962.jpg?fit=crop\u0026h=300\u0026w=300","UnitPrice":1.20,"UnitPriceString":"1,20 \u20AC/ud.","ReferencePrice":1.20,"ReferencePriceString":"1,20 \u20AC/kg","Packaging":"Paquete 200 g","CategoryIds":[15,133,479]},{"Id":"34822","Name":"Palomitas de ma\u00EDz con sal Hacendado para microondas","ShareUrl":"https://tienda.mercadona.es/product/34822/palomitas-maiz-con-sal-hacendado-microondas-paquete","Thumbnail":"https://prod-mercadona.imgix.net/images/9e583cb8ebd7e7f2e2cd698f1ed0d549.jpg?fit=crop\u0026h=300\u0026w=300","UnitPrice":1.10,"UnitPriceString":"1,10 \u20AC/ud.","ReferencePrice":1.10,"ReferencePriceString":"1,10 \u20AC/kg","Packaging":"Paquete 3 ud. (270 g)","CategoryIds":[15,133,479]},{"Id":"34027","Name":"Anacardo frito salado Hacendado","ShareUrl":"https://tienda.mercadona.es/product/34027/anacardo-frito-salado-hacendado-paquete","Thumbnail":"https://prod-mercadona.imgix.net/images/c8d06999d4d13e85ea28af4d60ed49cb.jpg?fit=crop\u0026h=300\u0026w=300","UnitPrice":2.40,"UnitPriceString":"2,40 \u20AC/ud.","ReferencePrice":2.40,"ReferencePriceString":"2,40 \u20AC/kg","Packaging":"Paquete 200 g","CategoryIds":[15,133,479]},{"Id":"34025","Name":"Avellana tostada Hacendado 0% sal a\u00F1adida","ShareUrl":"https://tienda.mercadona.es/product/34025/avellana-tostada-hacendado-0-sal-anadida-paquete","Thumbnail":"https://prod-mercadona.imgix.net/images/2fe6ffcc848dc8e5e28ed47bcec81a4b.jpg?fit=crop\u0026h=300\u0026w=300","UnitPrice":2.80,"UnitPriceString":"2,80 \u20AC/ud.","ReferencePrice":2.80,"ReferencePriceString":"2,80 \u20AC/kg","Packaging":"Paquete 200 g","CategoryIds":[15,133,479]},{"Id":"34013","Name":"Almendra tostada y salada Hacendado con piel","ShareUrl":"https://tienda.mercadona.es/product/34013/almendra-tostada-salada-hacendado-con-piel-paquete","Thumbnail":"https://prod-mercadona.imgix.net/images/30c38543e5bee4651190c69c0bd611d4.jpg?fit=crop\u0026h=300\u0026w=300","UnitPrice":2.80,"UnitPriceString":"2,80 \u20AC/ud.","ReferencePrice":2.80,"ReferencePriceString":"2,80 \u20AC/kg","Packaging":"Paquete 200 g","CategoryIds":[15,133,479]},{"Id":"34868","Name":"Cacahuete frito y salado Hacendado con piel","ShareUrl":"https://tienda.mercadona.es/product/34868/cacahuete-frito-salado-hacendado-con-piel-paquete","Thumbnail":"https://prod-mercadona.imgix.net/images/9ba31472c3bc97cad3c8f6bce8181942.jpg?fit=crop\u0026h=300\u0026w=300","UnitPrice":1.30,"UnitPriceString":"1,30 \u20AC/ud.","ReferencePrice":1.30,"ReferencePriceString":"1,30 \u20AC/kg","Packaging":"Paquete 250 g","CategoryIds":[15,133,479]},{"Id":"34821","Name":"Ma\u00EDz frito crujiente y tierno Hacendado","ShareUrl":"https://tienda.mercadona.es/product/34821/maiz-frito-crujiente-tierno-hacendado-paquete","Thumbnail":"https://prod-mercadona.imgix.net/images/3c7833d0fe0ae3384a8726eda5152cb8.jpg?fit=crop\u0026h=300\u0026w=300","UnitPrice":1.00,"UnitPriceString":"1,00 \u20AC/ud.","ReferencePrice":1.00,"ReferencePriceString":"1,00 \u20AC/kg","Packaging":"Paquete 170 g","CategoryIds":[15,133,479]},{"Id":"34009","Name":"Almendra frita y salada Hacendado pelada","ShareUrl":"https://tienda.mercadona.es/product/34009/almendra-frita-salada-hacendado-pelada-paquete","Thumbnail":"https://prod-mercadona.imgix.net/images/18b252be95928fd4239312aefb7426cc.jpg?fit=crop\u0026h=300\u0026w=300","UnitPrice":2.55,"UnitPriceString":"2,55 \u20AC/ud.","ReferencePrice":2.55,"ReferencePriceString":"2,55 \u20AC/kg","Packaging":"Paquete 200 g","CategoryIds":[15,133,479]},{"Id":"34031","Name":"Cacahuete tostado Hacendado 0% sal a\u00F1adida","ShareUrl":"https://tienda.mercadona.es/product/34031/cacahuete-tostado-hacendado-0-sal-anadida-paquete","Thumbnail":"https://prod-mercadona.imgix.net/images/09cec547e9ac6bbfa54ada3a03176248.jpg?fit=crop\u0026h=300\u0026w=300","UnitPrice":1.60,"UnitPriceString":"1,60 \u20AC/ud.","ReferencePrice":1.60,"ReferencePriceString":"1,60 \u20AC/kg","Packaging":"Paquete 400 g","CategoryIds":[15,133,479]},{"Id":"34014","Name":"Almendra tostada Hacendado 0% sal a\u00F1adida con piel","ShareUrl":"https://tienda.mercadona.es/product/34014/almendra-tostada-hacendado-0-sal-anadida-con-piel-paquete","Thumbnail":"https://prod-mercadona.imgix.net/images/7a77ef505d74e25cafc5baf23b07beed.jpg?fit=crop\u0026h=300\u0026w=300","UnitPrice":2.80,"UnitPriceString":"2,80 \u20AC/ud.","ReferencePrice":2.80,"ReferencePriceString":"2,80 \u20AC/kg","Packaging":"Paquete 200 g","CategoryIds":[15,133,479]},{"Id":"34804","Name":"Ma\u00EDz palomitas Hacendado","ShareUrl":"https://tienda.mercadona.es/product/34804/maiz-palomitas-hacendado-paquete","Thumbnail":"https://prod-mercadona.imgix.net/images/a0ad6f19c226b0b8f3f9e10716d6b154.jpg?fit=crop\u0026h=300\u0026w=300","UnitPrice":0.82,"UnitPriceString":"0,82 \u20AC/ud.","ReferencePrice":0.82,"ReferencePriceString":"0,82 \u20AC/kg","Packaging":"Paquete 250 g","CategoryIds":[15,133,479]},{"Id":"34838","Name":"Nuez macadamia Hacendado tostada con sal","ShareUrl":"https://tienda.mercadona.es/product/34838/nuez-macadamia-hacendado-tostada-con-sal-paquete","Thumbnail":"https://prod-mercadona.imgix.net/images/d2a3fcce740927f65023edbf64335dec.jpg?fit=crop\u0026h=300\u0026w=300","UnitPrice":2.65,"UnitPriceString":"2,65 \u20AC/ud.","ReferencePrice":2.65,"ReferencePriceString":"2,65 \u20AC/kg","Packaging":"Paquete 100 g","CategoryIds":[15,133,479]},{"Id":"34188","Name":"Pipas de calabaza natural Hacendado peladas","ShareUrl":"https://tienda.mercadona.es/product/34188/pipas-calabaza-natural-hacendado-peladas-paquete","Thumbnail":"https://prod-mercadona.imgix.net/images/29e68facc14597737f938b7ae808d844.jpg?fit=crop\u0026h=300\u0026w=300","UnitPrice":1.63,"UnitPriceString":"1,63 \u20AC/ud.","ReferencePrice":1.63,"ReferencePriceString":"1,63 \u20AC/kg","Packaging":"Paquete 150 g","CategoryIds":[15,133,479]},{"Id":"34194","Name":"Casta\u00F1as cocidas y peladas Hacendado","ShareUrl":"https://tienda.mercadona.es/product/34194/castanas-cocidas-peladas-hacendado-paquete","Thumbnail":"https://prod-mercadona.imgix.net/images/32836742fb49fae5f2235e0f3fa40a58.jpg?fit=crop\u0026h=300\u0026w=300","UnitPrice":1.40,"UnitPriceString":"1,40 \u20AC/ud.","ReferencePrice":1.40,"ReferencePriceString":"1,40 \u20AC/kg","Packaging":"Paquete 100 g","CategoryIds":[15,133,479]},{"Id":"34143","Name":"Cacahuete frito con miel Hacendado","ShareUrl":"https://tienda.mercadona.es/product/34143/cacahuete-frito-con-miel-hacendado-paquete","Thumbnail":"https://prod-mercadona.imgix.net/images/c3b2fa510948ac7bcb676f888d109f5f.jpg?fit=crop\u0026h=300\u0026w=300","UnitPrice":1.65,"UnitPriceString":"1,65 \u20AC/ud.","ReferencePrice":1.65,"ReferencePriceString":"1,65 \u20AC/kg","Packaging":"Paquete 200 g","CategoryIds":[15,133,479]},{"Id":"34016","Name":"Cacahuete tostado con sal Hacendado","ShareUrl":"https://tienda.mercadona.es/product/34016/cacahuete-tostado-con-sal-hacendado-paquete","Thumbnail":"https://prod-mercadona.imgix.net/images/b335759dffb927abd3ea0b2c13deafa9.jpg?fit=crop\u0026h=300\u0026w=300","UnitPrice":1.60,"UnitPriceString":"1,60 \u20AC/ud.","ReferencePrice":1.60,"ReferencePriceString":"1,60 \u20AC/kg","Packaging":"Paquete 400 g","CategoryIds":[15,133,479]},{"Id":"34961","Name":"Semillas ch\u00EDa Hacendado","ShareUrl":"https://tienda.mercadona.es/product/34961/semillas-chia-hacendado-paquete","Thumbnail":"https://prod-mercadona.imgix.net/images/0e639a215c522284117d8c5047b92526.jpg?fit=crop\u0026h=300\u0026w=300","UnitPrice":1.35,"UnitPriceString":"1,35 \u20AC/ud.","ReferencePrice":1.35,"ReferencePriceString":"1,35 \u20AC/kg","Packaging":"Paquete 150 g","CategoryIds":[15,133,479]},{"Id":"34145","Name":"Pipas de girasol fritas Hacendado peladas","ShareUrl":"https://tienda.mercadona.es/product/34145/pipas-girasol-fritas-hacendado-peladas-paquete","Thumbnail":"https://prod-mercadona.imgix.net/images/ab599ff93d3e90f8740a94b75f44e1b7.jpg?fit=crop\u0026h=300\u0026w=300","UnitPrice":1.10,"UnitPriceString":"1,10 \u20AC/ud.","ReferencePrice":1.10,"ReferencePriceString":"1,10 \u20AC/kg","Packaging":"Paquete 200 g","CategoryIds":[15,133,479]},{"Id":"34212","Name":"Palomitas de ma\u00EDz sabor mantequilla Hacendado para microondas","ShareUrl":"https://tienda.mercadona.es/product/34212/palomitas-maiz-sabor-mantequilla-hacendado-microondas-paquete","Thumbnail":"https://prod-mercadona.imgix.net/images/a61b56352cf06733952e4e5a59ad0cde.jpg?fit=crop\u0026h=300\u0026w=300","UnitPrice":1.35,"UnitPriceString":"1,35 \u20AC/ud.","ReferencePrice":1.35,"ReferencePriceString":"1,35 \u20AC/kg","Packaging":"Paquete 3 ud. (270 g)","CategoryIds":[15,133,479]},{"Id":"34164","Name":"Avellana natural Hacendado","ShareUrl":"https://tienda.mercadona.es/product/34164/avellana-natural-hacendado-paquete","Thumbnail":"https://prod-mercadona.imgix.net/images/bc77b1ffbaf2d9b814e46d7a02d0dfb5.jpg?fit=crop\u0026h=300\u0026w=300","UnitPrice":2.65,"UnitPriceString":"2,65 \u20AC/ud.","ReferencePrice":2.65,"ReferencePriceString":"2,65 \u20AC/kg","Packaging":"Paquete 200 g","CategoryIds":[15,133,479]},{"Id":"34964","Name":"Semillas s\u00E9samo tostado Hacendado","ShareUrl":"https://tienda.mercadona.es/product/34964/semillas-sesamo-tostado-hacendado-paquete","Thumbnail":"https://prod-mercadona.imgix.net/images/fb777e1d4a1c4070fec4002886f4d339.jpg?fit=crop\u0026h=300\u0026w=300","UnitPrice":1.40,"UnitPriceString":"1,40 \u20AC/ud.","ReferencePrice":1.40,"ReferencePriceString":"1,40 \u20AC/kg","Packaging":"Paquete 150 g","CategoryIds":[15,133,479]},{"Id":"34043","Name":"Pipas girasol barbacoa Hacendado","ShareUrl":"https://tienda.mercadona.es/product/34043/pipas-girasol-barbacoa-hacendado-paquete","Thumbnail":"https://prod-mercadona.imgix.net/images/0547d4315893a4abd17eee2610dd8c29.jpg?fit=crop\u0026h=300\u0026w=300","UnitPrice":1.35,"UnitPriceString":"1,35 \u20AC/ud.","ReferencePrice":1.35,"ReferencePriceString":"1,35 \u20AC/kg","Packaging":"Paquete 200 g","CategoryIds":[15,133,479]},{"Id":"34193","Name":"Pipas girasol naturales Hacendado peladas","ShareUrl":"https://tienda.mercadona.es/product/34193/pipas-girasol-naturales-hacendado-peladas-paquete","Thumbnail":"https://prod-mercadona.imgix.net/images/0c0426c30e108fd772328302f23d5459.jpg?fit=crop\u0026h=300\u0026w=300","UnitPrice":1.20,"UnitPriceString":"1,20 \u20AC/ud.","ReferencePrice":1.20,"ReferencePriceString":"1,20 \u20AC/kg","Packaging":"Paquete 200 g","CategoryIds":[15,133,479]},{"Id":"34606","Name":"Nuez natural Hacendado","ShareUrl":"https://tienda.mercadona.es/product/34606/nuez-natural-hacendado-paquete","Thumbnail":"https://prod-mercadona.imgix.net/images/d1899ae163ff39ebd4f7f1896a0478a7.jpg?fit=crop\u0026h=300\u0026w=300","UnitPrice":3.25,"UnitPriceString":"3,25 \u20AC/ud.","ReferencePrice":3.25,"ReferencePriceString":"3,25 \u20AC/kg","Packaging":"Paquete 600 g","CategoryIds":[15,133,479]},{"Id":"34095","Name":"Pipas calabaza tostadas Hacendado aguasal","ShareUrl":"https://tienda.mercadona.es/product/34095/pipas-calabaza-tostadas-hacendado-aguasal-paquete","Thumbnail":"https://prod-mercadona.imgix.net/images/640adb6de33762c72aa87643770bb4d0.jpg?fit=crop\u0026h=300\u0026w=300","UnitPrice":1.55,"UnitPriceString":"1,55 \u20AC/ud.","ReferencePrice":1.55,"ReferencePriceString":"1,55 \u20AC/kg","Packaging":"Paquete 125 g","CategoryIds":[15,133,479]},{"Id":"34236","Name":"Nuez de Brasil natural Hacendado","ShareUrl":"https://tienda.mercadona.es/product/34236/nuez-brasil-natural-hacendado-paquete","Thumbnail":"https://prod-mercadona.imgix.net/images/a6207de974d4e148bf80bdeb03a8a8e8.jpg?fit=crop\u0026h=300\u0026w=300","UnitPrice":3.37,"UnitPriceString":"3,37 \u20AC/ud.","ReferencePrice":3.37,"ReferencePriceString":"3,37 \u20AC/kg","Packaging":"Paquete 200 g","CategoryIds":[15,133,479]},{"Id":"34262","Name":"Pistacho natural Hacendado pelado","ShareUrl":"https://tienda.mercadona.es/product/34262/pistacho-natural-hacendado-pelado-paquete","Thumbnail":"https://prod-mercadona.imgix.net/images/30bfa5df47a47432c790f69e68bbf874.jpg?fit=crop\u0026h=300\u0026w=300","UnitPrice":2.64,"UnitPriceString":"2,64 \u20AC/ud.","ReferencePrice":2.64,"ReferencePriceString":"2,64 \u20AC/kg","Packaging":"Paquete 100 g","CategoryIds":[15,133,479]},{"Id":"34997","Name":"Nuez Pecana natural Hacendado pelada","ShareUrl":"https://tienda.mercadona.es/product/34997/nuez-pecana-natural-hacendado-pelada-paquete","Thumbnail":"https://prod-mercadona.imgix.net/images/29752e6cbeb65cbea2a6d7e7c9510a4d.jpg?fit=crop\u0026h=300\u0026w=300","UnitPrice":3.56,"UnitPriceString":"3,56 \u20AC/ud.","ReferencePrice":3.56,"ReferencePriceString":"3,56 \u20AC/kg","Packaging":"Paquete 200 g","CategoryIds":[15,133,479]},{"Id":"34817","Name":"Palomitas de ma\u00EDz dulces Hacendado para microondas","ShareUrl":"https://tienda.mercadona.es/product/34817/palomitas-maiz-dulces-hacendado-microondas-paquete","Thumbnail":"https://prod-mercadona.imgix.net/images/ac49fa3af792b6df698392dfeab2b954.jpg?fit=crop\u0026h=300\u0026w=300","UnitPrice":1.70,"UnitPriceString":"1,70 \u20AC/ud.","ReferencePrice":1.70,"ReferencePriceString":"1,70 \u20AC/kg","Packaging":"Paquete 3 ud. (315 g)","CategoryIds":[15,133,479]},{"Id":"34231","Name":"Cocktail mezcla Hacendado","ShareUrl":"https://tienda.mercadona.es/product/34231/cocktail-mezcla-hacendado-compuesto-maiz-cacahuetes-garbanzos-bolita-snack-pasas-sultanas-paquete","Thumbnail":"https://prod-mercadona.imgix.net/images/7765bf78ab98230c369f05a584b009c3.jpg?fit=crop\u0026h=300\u0026w=300","UnitPrice":1.60,"UnitPriceString":"1,60 \u20AC/ud.","ReferencePrice":1.60,"ReferencePriceString":"1,60 \u20AC/kg","Packaging":"Paquete 300 g","CategoryIds":[15,133,846]},{"Id":"34047","Name":"Cocktail crunchy sabores Hacendado","ShareUrl":"https://tienda.mercadona.es/product/34047/cocktail-crunchy-sabores-hacendado-paquete","Thumbnail":"https://prod-mercadona.imgix.net/images/abf53d0049f487f8dda1f1a58fe6f29f.jpg?fit=crop\u0026h=300\u0026w=300","UnitPrice":1.85,"UnitPriceString":"1,85 \u20AC/ud.","ReferencePrice":1.85,"ReferencePriceString":"1,85 \u20AC/kg","Packaging":"Paquete 200 g","CategoryIds":[15,133,846]},{"Id":"34217","Name":"Cocktail rodeo Hacendado","ShareUrl":"https://tienda.mercadona.es/product/34217/cocktail-rodeo-hacendado-paquete","Thumbnail":"https://prod-mercadona.imgix.net/images/9bcb162be0f6084bfd2d90741082ec08.jpg?fit=crop\u0026h=300\u0026w=300","UnitPrice":1.75,"UnitPriceString":"1,75 \u20AC/ud.","ReferencePrice":1.75,"ReferencePriceString":"1,75 \u20AC/kg","Packaging":"Paquete 250 g","CategoryIds":[15,133,846]},{"Id":"34924","Name":"Cocktail fruta deshidratada Hacendado","ShareUrl":"https://tienda.mercadona.es/product/34924/cocktail-fruta-deshidratada-hacendado-paquete","Thumbnail":"https://prod-mercadona.imgix.net/images/2b66d3da0e8bbf54cfe4f38388a1374b.jpg?fit=crop\u0026h=300\u0026w=300","UnitPrice":1.60,"UnitPriceString":"1,60 \u20AC/ud.","ReferencePrice":1.60,"ReferencePriceString":"1,60 \u20AC/kg","Packaging":"Paquete 200 g","CategoryIds":[15,133,846]},{"Id":"34209","Name":"Mango deshidratado Hacendado","ShareUrl":"https://tienda.mercadona.es/product/34209/mango-deshidratado-hacendado-sin-azucar-anadido-paquete","Thumbnail":"https://prod-mercadona.imgix.net/images/07b71e82fa94f42ca1a285c371124656.jpg?fit=crop\u0026h=300\u0026w=300","UnitPrice":1.35,"UnitPriceString":"1,35 \u20AC/ud.","ReferencePrice":1.35,"ReferencePriceString":"1,35 \u20AC/kg","Packaging":"Paquete 60 g","CategoryIds":[15,133,483]},{"Id":"34605","Name":"Ar\u00E1ndanos deshidratados Hacendado","ShareUrl":"https://tienda.mercadona.es/product/34605/arandanos-deshidratados-hacendado-paquete","Thumbnail":"https://prod-mercadona.imgix.net/images/92f5beabf47df2524be72894b90885bc.jpg?fit=crop\u0026h=300\u0026w=300","UnitPrice":2.40,"UnitPriceString":"2,40 \u20AC/ud.","ReferencePrice":2.40,"ReferencePriceString":"2,40 \u20AC/kg","Packaging":"Paquete 200 g","CategoryIds":[15,133,483]},{"Id":"34135","Name":"Higo seco Valle del Jerte","ShareUrl":"https://tienda.mercadona.es/product/34135/higo-seco-valle-jerte-paquete","Thumbnail":"https://prod-mercadona.imgix.net/images/5dc394a800c49f1b4ac2499c28b4c853.jpg?fit=crop\u0026h=300\u0026w=300","UnitPrice":2.15,"UnitPriceString":"2,15 \u20AC/ud.","ReferencePrice":2.15,"ReferencePriceString":"2,15 \u20AC/kg","Packaging":"Paquete 500 g","CategoryIds":[15,133,483]},{"Id":"34811","Name":"Palomitas caramelo Hacendado","ShareUrl":"https://tienda.mercadona.es/product/34811/palomitas-caramelo-hacendado-paquete","Thumbnail":"https://prod-mercadona.imgix.net/images/54f08a75c350854e471b9f2b73b92a5d.jpg?fit=crop\u0026h=300\u0026w=300","UnitPrice":1.30,"UnitPriceString":"1,30 \u20AC/ud.","ReferencePrice":1.30,"ReferencePriceString":"1,30 \u20AC/kg","Packaging":"Paquete 120 g","CategoryIds":[15,132,475]},{"Id":"34046","Name":"Bolas de cereal ba\u00F1adas Hacendado de chocolate negro, con leche y blanco","ShareUrl":"https://tienda.mercadona.es/product/34046/bolas-cereal-banadas-hacendado-chocolate-negro-con-leche-blanco-paquete","Thumbnail":"https://prod-mercadona.imgix.net/images/da1ac26bc66c335108870ce83fbd3122.jpg?fit=crop\u0026h=300\u0026w=300","UnitPrice":2.00,"UnitPriceString":"2,00 \u20AC/ud.","ReferencePrice":2.00,"ReferencePriceString":"2,00 \u20AC/kg","Packaging":"Paquete 200 g","CategoryIds":[9,92,386]},{"Id":"3497","Name":"Arreglo para puchero vacuno, cerdo y pollo","ShareUrl":"https://tienda.mercadona.es/product/3497/arreglo-puchero-vacuno-cerdo-pollo-bandeja","Thumbnail":"https://prod-mercadona.imgix.net/images/bc163ece659b8172611657c8dd05a9ca.jpg?fit=crop\u0026h=300\u0026w=300","UnitPrice":5.60,"UnitPriceString":"5,60 \u20AC/ud.","ReferencePrice":5.60,"ReferencePriceString":"5,60 \u20AC/kg","Packaging":"Bandeja 1 kg","CategoryIds":[3,46,289]},{"Id":"3496","Name":"Hueso vacuno","ShareUrl":"https://tienda.mercadona.es/product/3496/hueso-vacuno-bandeja","Thumbnail":"https://prod-mercadona.imgix.net/images/a92d2c027a7a79db860cef2cc0a0409f.jpg?fit=crop\u0026h=300\u0026w=300","UnitPrice":1.05,"UnitPriceString":"1,05 \u20AC/ud.","ReferencePrice":1.05,"ReferencePriceString":"1,05 \u20AC/kg","Packaging":"Bandeja 250 g","CategoryIds":[3,46,289]},{"Id":"3499","Name":"Costilla de vacuno","ShareUrl":"https://tienda.mercadona.es/product/3499/costilla-vacuno-bandeja","Thumbnail":"https://prod-mercadona.imgix.net/images/53acc81fc1295efedd264d724f582170.jpg?fit=crop\u0026h=300\u0026w=300","UnitPrice":2.49,"UnitPriceString":"2,49 \u20AC/ud.","ReferencePrice":2.49,"ReferencePriceString":"2,49 \u20AC/kg","Packaging":"Bandeja 250 g","CategoryIds":[3,46,289]},{"Id":"3400","Name":"Filetes pechuga de pollo corte fino","ShareUrl":"https://tienda.mercadona.es/product/3400/filetes-pechuga-pollo-corte-fino-minimo-10-filetes-bandeja","Thumbnail":"https://prod-mercadona.imgix.net/images/905302323a51ea295e2dc0a524791ac4.jpg?fit=crop\u0026h=300\u0026w=300","UnitPrice":4.40,"UnitPriceString":"4,40 \u20AC/ud.","ReferencePrice":4.40,"ReferencePriceString":"4,40 \u20AC/kg","Packaging":"Bandeja 500 g","CategoryIds":[3,38,281]},{"Id":"3440","Name":"Filetes lomo al ajillo","ShareUrl":"https://tienda.mercadona.es/product/3440/filetes-lomo-ajillo-bandeja","Thumbnail":"https://prod-mercadona.imgix.net/images/836f9cfc6d5bb25d16128e6efc156d46.jpg?fit=crop\u0026h=300\u0026w=300","UnitPrice":3.88,"UnitPriceString":"3,88 \u20AC/ud.","ReferencePrice":3.88,"ReferencePriceString":"3,88 \u20AC/kg","Packaging":"Bandeja 500 g","CategoryIds":[3,37,280]},{"Id":"3453","Name":"Preparado de carne picada vacuno y cerdo","ShareUrl":"https://tienda.mercadona.es/product/3453/preparado-carne-picada-vacuno-cerdo-bandeja","Thumbnail":"https://prod-mercadona.imgix.net/images/d9232bbd40c478422502a84b6354e873.jpg?fit=crop\u0026h=300\u0026w=300","UnitPrice":6.50,"UnitPriceString":"6,50 \u20AC/ud.","ReferencePrice":6.50,"ReferencePriceString":"6,50 \u20AC/kg","Packaging":"Bandeja 1 kg","CategoryIds":[3,44,783]},{"Id":"3454","Name":"Preparado de carne picada vacuno","ShareUrl":"https://tienda.mercadona.es/product/3454/preparado-carne-picada-vacuno-bandeja","Thumbnail":"https://prod-mercadona.imgix.net/images/2904785cb711a90a52734a54eeeb65f8.jpg?fit=crop\u0026h=300\u0026w=300","UnitPrice":7.45,"UnitPriceString":"7,45 \u20AC/ud.","ReferencePrice":7.45,"ReferencePriceString":"7,45 \u20AC/kg","Packaging":"Bandeja 1 kg","CategoryIds":[3,44,783]},{"Id":"3461","Name":"Entrecot de vacuno a\u00F1ojo fino para barbacoa o plancha","ShareUrl":"https://tienda.mercadona.es/product/3461/entrecot-vacuno-anojo-fino-barbacoa-plancha-bandeja","Thumbnail":"https://prod-mercadona.imgix.net/images/b6f612b1d62525fe7429d19896d65838.jpg?fit=crop\u0026h=300\u0026w=300","UnitPrice":10.95,"UnitPriceString":"10,95 \u20AC/ud.","ReferencePrice":10.95,"ReferencePriceString":"10,95 \u20AC/kg","Packaging":"Bandeja 500 g","CategoryIds":[3,40,283]},{"Id":"3460","Name":"Entrecot de vacuno a\u00F1ojo grueso para barbacoa o plancha","ShareUrl":"https://tienda.mercadona.es/product/3460/entrecot-vacuno-anojo-grueso-barbacoa-plancha-bandeja","Thumbnail":"https://prod-mercadona.imgix.net/images/6e57aa4f455c93f71ccd9979665dc0a6.jpg?fit=crop\u0026h=300\u0026w=300","UnitPrice":13.14,"UnitPriceString":"13,14 \u20AC/ud.","ReferencePrice":13.14,"ReferencePriceString":"13,14 \u20AC/kg","Packaging":"Bandeja 600 g","CategoryIds":[3,40,283]},{"Id":"3485","Name":"Naranjas","ShareUrl":"https://tienda.mercadona.es/product/3485/naranjas-malla","Thumbnail":"https://prod-mercadona.imgix.net/images/49ca2cb3eabe88f27e47646d723b2b16.jpg?fit=crop\u0026h=300\u0026w=300","UnitPrice":8.75,"UnitPriceString":"8,75 \u20AC/ud.","ReferencePrice":8.75,"ReferencePriceString":"8,75 \u20AC/kg","Packaging":"Malla 5 kg","CategoryIds":[1,27,247]},{"Id":"3422","Name":"Melocotones amarillos mini","ShareUrl":"https://tienda.mercadona.es/product/3422/melocotones-amarillos-mini-bandeja","Thumbnail":"https://prod-mercadona.imgix.net/images/d54c20f41141bc49fb6fbc0b064cf8bf.jpg?fit=crop\u0026h=300\u0026w=300","UnitPrice":2.59,"UnitPriceString":"2,59 \u20AC/pack","ReferencePrice":2.59,"ReferencePriceString":"2,59 \u20AC/kg","Packaging":"1 kg","CategoryIds":[1,27,253]},{"Id":"3433","Name":"Melocot\u00F3n amarillo","ShareUrl":"https://tienda.mercadona.es/product/3433/melocoton-amarillo-pieza","Thumbnail":"https://prod-mercadona.imgix.net/images/83528d0f0039f50dbf33ac7a3346161f.jpg?fit=crop\u0026h=300\u0026w=300","UnitPrice":0.54,"UnitPriceString":"0,54 \u20AC/ud.","ReferencePrice":0.54,"ReferencePriceString":"0,54 \u20AC/kg","Packaging":"Pieza 180 g","CategoryIds":[1,27,253]},{"Id":"34921","Name":"Almendra molida Hacendado","ShareUrl":"https://tienda.mercadona.es/product/34921/almendra-molida-hacendado-paquete","Thumbnail":"https://prod-mercadona.imgix.net/images/e981738e3b8397ebb3fa516148a66768.jpg?fit=crop\u0026h=300\u0026w=300","UnitPrice":2.07,"UnitPriceString":"2,07 \u20AC/ud.","ReferencePrice":2.07,"ReferencePriceString":"2,07 \u20AC/kg","Packaging":"Paquete 125 g","CategoryIds":[5,71,340]},{"Id":"34035","Name":"Coco rallado Hacendado","ShareUrl":"https://tienda.mercadona.es/product/34035/coco-rallado-hacendado-paquete","Thumbnail":"https://prod-mercadona.imgix.net/images/17a3c5a1186ddd174b059668c48c859c.jpg?fit=crop\u0026h=300\u0026w=300","UnitPrice":1.10,"UnitPriceString":"1,10 \u20AC/ud.","ReferencePrice":1.10,"ReferencePriceString":"1,10 \u20AC/kg","Packaging":"Paquete 125 g","CategoryIds":[5,71,340]},{"Id":"34922","Name":"Almendra cubitos Hacendado","ShareUrl":"https://tienda.mercadona.es/product/34922/almendra-cubitos-hacendado-paquete","Thumbnail":"https://prod-mercadona.imgix.net/images/5292b4bd80ffede0615f20b5ca377eb7.jpg?fit=crop\u0026h=300\u0026w=300","UnitPrice":2.07,"UnitPriceString":"2,07 \u20AC/ud.","ReferencePrice":2.07,"ReferencePriceString":"2,07 \u20AC/kg","Packaging":"Paquete 125 g","CategoryIds":[5,71,340]},{"Id":"34923","Name":"Almendra laminada Hacendado","ShareUrl":"https://tienda.mercadona.es/product/34923/almendra-laminada-hacendado-paquete","Thumbnail":"https://prod-mercadona.imgix.net/images/4df12766bc1ccb08aeacf84afdd4223e.jpg?fit=crop\u0026h=300\u0026w=300","UnitPrice":2.07,"UnitPriceString":"2,07 \u20AC/ud.","ReferencePrice":2.07,"ReferencePriceString":"2,07 \u20AC/kg","Packaging":"Paquete 125 g","CategoryIds":[5,71,340]}]